[
    {
        "cls_id": "CE01310",
        "url": "https://coursesearch04.fcu.edu.tw/CourseOutline.aspx?lang=cht&courseid=1033CE0131043130001"
    },
    {
        "cls_id": "CE01310",
        "url": "https://coursesearch04.fcu.edu.tw/CourseOutline.aspx?lang=cht&courseid=1033CE0131002855001"
    },
    {
        "cls_id": "CE01310",
        "url": "https://coursesearch04.fcu.edu.tw/CourseOutline.aspx?lang=cht&courseid=1033CE0131032810001"
    },
    {
        "cls_id": "CE01310",
        "url": "https://coursesearch04.fcu.edu.tw/CourseOutline.aspx?lang=cht&courseid=1033CE0131045695001"
    },
    {
        "cls_id": "CE01310",
        "url": "https://coursesearch04.fcu.edu.tw/CourseOutline.aspx?lang=cht&courseid=1033CE0131045701001"
    },
    {
        "cls_id": "CE01310",
        "url": "https://coursesearch04.fcu.edu.tw/CourseOutline.aspx?lang=cht&courseid=1033CE0131047760001"
    },
    {
        "cls_id": "CE01310",
        "url": "https://coursesearch04.fcu.edu.tw/CourseOutline.aspx?lang=cht&courseid=1033CE0131062658001"
    },
    {
        "cls_id": "CE01310",
        "url": "https://coursesearch04.fcu.edu.tw/CourseOutline.aspx?lang=cht&courseid=1033CE0131068900001"
    },
    {
        "cls_id": "CE01310",
        "url": "https://coursesearch04.fcu.edu.tw/CourseOutline.aspx?lang=cht&courseid=1033CE0131004345001"
    },
    {
        "cls_id": "CE01310",
        "url": "https://coursesearch04.fcu.edu.tw/CourseOutline.aspx?lang=cht&courseid=1033CE0131011140001"
    },
    {
        "cls_id": "CE01310",
        "url": "https://coursesearch04.fcu.edu.tw/CourseOutline.aspx?lang=cht&courseid=1033CE0131016600001"
    },
    {
        "cls_id": "CE0131A",
        "url": "https://coursesearch04.fcu.edu.tw/CourseOutline.aspx?lang=cht&courseid=1033CE0131A43130001"
    },
    {
        "cls_id": "CE0131A",
        "url": "https://coursesearch04.fcu.edu.tw/CourseOutline.aspx?lang=cht&courseid=1033CE0131A04345001"
    },
    {
        "cls_id": "CE0131A",
        "url": "https://coursesearch04.fcu.edu.tw/CourseOutline.aspx?lang=cht&courseid=1033CE0131A11140001"
    },
    {
        "cls_id": "CE0131A",
        "url": "https://coursesearch04.fcu.edu.tw/CourseOutline.aspx?lang=cht&courseid=1033CE0131A16600001"
    },
    {
        "cls_id": "CE0131A",
        "url": "https://coursesearch04.fcu.edu.tw/CourseOutline.aspx?lang=cht&courseid=1033CE0131A30972001"
    },
    {
        "cls_id": "CE01320",
        "url": "https://coursesearch04.fcu.edu.tw/CourseOutline.aspx?lang=cht&courseid=1033CE0132061530001"
    },
    {
        "cls_id": "CE01320",
        "url": "https://coursesearch04.fcu.edu.tw/CourseOutline.aspx?lang=cht&courseid=1033CE0132023191001"
    },
    {
        "cls_id": "CE01320",
        "url": "https://coursesearch04.fcu.edu.tw/CourseOutline.aspx?lang=cht&courseid=1033CE0132043131001"
    },
    {
        "cls_id": "CE01320",
        "url": "https://coursesearch04.fcu.edu.tw/CourseOutline.aspx?lang=cht&courseid=1033CE0132051493001"
    },
    {
        "cls_id": "CE01320",
        "url": "https://coursesearch04.fcu.edu.tw/CourseOutline.aspx?lang=cht&courseid=1033CE0132065100001"
    },
    {
        "cls_id": "CE0132A",
        "url": "https://coursesearch04.fcu.edu.tw/CourseOutline.aspx?lang=cht&courseid=1033CE0132A61530001"
    },
    {
        "cls_id": "CE0132A",
        "url": "https://coursesearch04.fcu.edu.tw/CourseOutline.aspx?lang=cht&courseid=1033CE0132A40711001"
    },
    {
        "cls_id": "CE0132A",
        "url": "https://coursesearch04.fcu.edu.tw/CourseOutline.aspx?lang=cht&courseid=1033CE0132A43131001"
    },
    {
        "cls_id": "CE02310",
        "url": "https://coursesearch04.fcu.edu.tw/CourseOutline.aspx?lang=cht&courseid=1033CE0231027162001"
    },
    {
        "cls_id": "CE02310",
        "url": "https://coursesearch04.fcu.edu.tw/CourseOutline.aspx?lang=cht&courseid=1033CE0231043130001"
    },
    {
        "cls_id": "CE02310",
        "url": "https://coursesearch04.fcu.edu.tw/CourseOutline.aspx?lang=cht&courseid=1033CE0231001951001"
    },
    {
        "cls_id": "CE02310",
        "url": "https://coursesearch04.fcu.edu.tw/CourseOutline.aspx?lang=cht&courseid=1033CE0231004660001"
    },
    {
        "cls_id": "CE02310",
        "url": "https://coursesearch04.fcu.edu.tw/CourseOutline.aspx?lang=cht&courseid=1033CE0231009363001"
    },
    {
        "cls_id": "CE02310",
        "url": "https://coursesearch04.fcu.edu.tw/CourseOutline.aspx?lang=cht&courseid=1033CE0231027870001"
    },
    {
        "cls_id": "CE02310",
        "url": "https://coursesearch04.fcu.edu.tw/CourseOutline.aspx?lang=cht&courseid=1033CE0231035372001"
    },
    {
        "cls_id": "CE02320",
        "url": "https://coursesearch04.fcu.edu.tw/CourseOutline.aspx?lang=cht&courseid=1033CE0232061530001"
    },
    {
        "cls_id": "CE02320",
        "url": "https://coursesearch04.fcu.edu.tw/CourseOutline.aspx?lang=cht&courseid=1033CE0232010260001"
    },
    {
        "cls_id": "CE02320",
        "url": "https://coursesearch04.fcu.edu.tw/CourseOutline.aspx?lang=cht&courseid=1033CE0232010761001"
    },
    {
        "cls_id": "CE02320",
        "url": "https://coursesearch04.fcu.edu.tw/CourseOutline.aspx?lang=cht&courseid=1033CE0232043131001"
    },
    {
        "cls_id": "CE03310",
        "url": "https://coursesearch04.fcu.edu.tw/CourseOutline.aspx?lang=cht&courseid=1033CE0331026210001"
    },
    {
        "cls_id": "CE03310",
        "url": "https://coursesearch04.fcu.edu.tw/CourseOutline.aspx?lang=cht&courseid=1033CE0331043130001"
    },
    {
        "cls_id": "CE03310",
        "url": "https://coursesearch04.fcu.edu.tw/CourseOutline.aspx?lang=cht&courseid=1033CE0331074281001"
    },
    {
        "cls_id": "CE03310",
        "url": "https://coursesearch04.fcu.edu.tw/CourseOutline.aspx?lang=cht&courseid=1033CE0331005040001"
    },
    {
        "cls_id": "CE03310",
        "url": "https://coursesearch04.fcu.edu.tw/CourseOutline.aspx?lang=cht&courseid=1033CE0331021915001"
    },
    {
        "cls_id": "CE03310",
        "url": "https://coursesearch04.fcu.edu.tw/CourseOutline.aspx?lang=cht&courseid=1033CE0331074211001"
    },
    {
        "cls_id": "CE0331A",
        "url": "https://coursesearch04.fcu.edu.tw/CourseOutline.aspx?lang=cht&courseid=1033CE0331A43130001"
    },
    {
        "cls_id": "CE0331A",
        "url": "https://coursesearch04.fcu.edu.tw/CourseOutline.aspx?lang=cht&courseid=1033CE0331A26352001"
    },
    {
        "cls_id": "CE0331A",
        "url": "https://coursesearch04.fcu.edu.tw/CourseOutline.aspx?lang=cht&courseid=1033CE0331A69021001"
    },
    {
        "cls_id": "CE0331A",
        "url": "https://coursesearch04.fcu.edu.tw/CourseOutline.aspx?lang=cht&courseid=1033CE0331A26210001"
    },
    {
        "cls_id": "CE03320",
        "url": "https://coursesearch04.fcu.edu.tw/CourseOutline.aspx?lang=cht&courseid=1033CE0332049861001"
    },
    {
        "cls_id": "CE03320",
        "url": "https://coursesearch04.fcu.edu.tw/CourseOutline.aspx?lang=cht&courseid=1033CE0332043131001"
    },
    {
        "cls_id": "CE03320",
        "url": "https://coursesearch04.fcu.edu.tw/CourseOutline.aspx?lang=cht&courseid=1033CE0332061530001"
    },
    {
        "cls_id": "CE03320",
        "url": "https://coursesearch04.fcu.edu.tw/CourseOutline.aspx?lang=cht&courseid=1033CE0332023820001"
    },
    {
        "cls_id": "CE03320",
        "url": "https://coursesearch04.fcu.edu.tw/CourseOutline.aspx?lang=cht&courseid=1033CE0332065757001"
    },
    {
        "cls_id": "CE0332A",
        "url": "https://coursesearch04.fcu.edu.tw/CourseOutline.aspx?lang=cht&courseid=1033CE0332A43131001"
    },
    {
        "cls_id": "CE0332A",
        "url": "https://coursesearch04.fcu.edu.tw/CourseOutline.aspx?lang=cht&courseid=1033CE0332A61530001"
    },
    {
        "cls_id": "CE0332A",
        "url": "https://coursesearch04.fcu.edu.tw/CourseOutline.aspx?lang=cht&courseid=1033CE0332A46559001"
    },
    {
        "cls_id": "CM02310",
        "url": "https://coursesearch04.fcu.edu.tw/CourseOutline.aspx?lang=cht&courseid=1033CM0231027162001"
    },
    {
        "cls_id": "CM02310",
        "url": "https://coursesearch04.fcu.edu.tw/CourseOutline.aspx?lang=cht&courseid=1033CM0231059121001"
    },
    {
        "cls_id": "CM02310",
        "url": "https://coursesearch04.fcu.edu.tw/CourseOutline.aspx?lang=cht&courseid=1033CM0231006520001"
    },
    {
        "cls_id": "CM02310",
        "url": "https://coursesearch04.fcu.edu.tw/CourseOutline.aspx?lang=cht&courseid=1033CM0231022617001"
    },
    {
        "cls_id": "CM02310",
        "url": "https://coursesearch04.fcu.edu.tw/CourseOutline.aspx?lang=cht&courseid=1033CM0231035783001"
    },
    {
        "cls_id": "CM02310",
        "url": "https://coursesearch04.fcu.edu.tw/CourseOutline.aspx?lang=cht&courseid=1033CM0231046260001"
    },
    {
        "cls_id": "CM02310",
        "url": "https://coursesearch04.fcu.edu.tw/CourseOutline.aspx?lang=cht&courseid=1033CM0231051510001"
    },
    {
        "cls_id": "CM0231A",
        "url": "https://coursesearch04.fcu.edu.tw/CourseOutline.aspx?lang=cht&courseid=1033CM0231A26210001"
    },
    {
        "cls_id": "CM0231A",
        "url": "https://coursesearch04.fcu.edu.tw/CourseOutline.aspx?lang=cht&courseid=1033CM0231A35601001"
    },
    {
        "cls_id": "CM02320",
        "url": "https://coursesearch04.fcu.edu.tw/CourseOutline.aspx?lang=cht&courseid=1033CM0232043130001"
    },
    {
        "cls_id": "CM02320",
        "url": "https://coursesearch04.fcu.edu.tw/CourseOutline.aspx?lang=cht&courseid=1033CM0232061530001"
    },
    {
        "cls_id": "CM02320",
        "url": "https://coursesearch04.fcu.edu.tw/CourseOutline.aspx?lang=cht&courseid=1033CM0232012951001"
    },
    {
        "cls_id": "CM0232A",
        "url": "https://coursesearch04.fcu.edu.tw/CourseOutline.aspx?lang=cht&courseid=1033CM0232A61530001"
    },
    {
        "cls_id": "CM0232A",
        "url": "https://coursesearch04.fcu.edu.tw/CourseOutline.aspx?lang=cht&courseid=1033CM0232A68801001"
    },
    {
        "cls_id": "CM0232A",
        "url": "https://coursesearch04.fcu.edu.tw/CourseOutline.aspx?lang=cht&courseid=1033CM0232A06551001"
    },
    {
        "cls_id": "CM0232A",
        "url": "https://coursesearch04.fcu.edu.tw/CourseOutline.aspx?lang=cht&courseid=1033CM0232A35784001"
    },
    {
        "cls_id": "CM0232A",
        "url": "https://coursesearch04.fcu.edu.tw/CourseOutline.aspx?lang=cht&courseid=1033CM0232A59003001"
    },
    {
        "cls_id": "CE10310",
        "url": "https://coursesearch04.fcu.edu.tw/CourseOutline.aspx?lang=cht&courseid=1033CE1031026210001"
    },
    {
        "cls_id": "CE10310",
        "url": "https://coursesearch04.fcu.edu.tw/CourseOutline.aspx?lang=cht&courseid=1033CE1031043130001"
    },
    {
        "cls_id": "CE10310",
        "url": "https://coursesearch04.fcu.edu.tw/CourseOutline.aspx?lang=cht&courseid=1033CE1031012953001"
    },
    {
        "cls_id": "CE10310",
        "url": "https://coursesearch04.fcu.edu.tw/CourseOutline.aspx?lang=cht&courseid=1033CE1031020946001"
    },
    {
        "cls_id": "CE10310",
        "url": "https://coursesearch04.fcu.edu.tw/CourseOutline.aspx?lang=cht&courseid=1033CE1031046463001"
    },
    {
        "cls_id": "CE10310",
        "url": "https://coursesearch04.fcu.edu.tw/CourseOutline.aspx?lang=cht&courseid=1033CE1031046558001"
    },
    {
        "cls_id": "CE10310",
        "url": "https://coursesearch04.fcu.edu.tw/CourseOutline.aspx?lang=cht&courseid=1033CE1031046705001"
    },
    {
        "cls_id": "CE10310",
        "url": "https://coursesearch04.fcu.edu.tw/CourseOutline.aspx?lang=cht&courseid=1033CE1031048890001"
    },
    {
        "cls_id": "CE10310",
        "url": "https://coursesearch04.fcu.edu.tw/CourseOutline.aspx?lang=cht&courseid=1033CE1031058855001"
    },
    {
        "cls_id": "CE1031A",
        "url": "https://coursesearch04.fcu.edu.tw/CourseOutline.aspx?lang=cht&courseid=1033CE1031A46463001"
    },
    {
        "cls_id": "CE1031A",
        "url": "https://coursesearch04.fcu.edu.tw/CourseOutline.aspx?lang=cht&courseid=1033CE1031A46558001"
    },
    {
        "cls_id": "CE1031A",
        "url": "https://coursesearch04.fcu.edu.tw/CourseOutline.aspx?lang=cht&courseid=1033CE1031A26210001"
    },
    {
        "cls_id": "CE1031A",
        "url": "https://coursesearch04.fcu.edu.tw/CourseOutline.aspx?lang=cht&courseid=1033CE1031A20946001"
    },
    {
        "cls_id": "CE10320",
        "url": "https://coursesearch04.fcu.edu.tw/CourseOutline.aspx?lang=cht&courseid=1033CE1032061530001"
    },
    {
        "cls_id": "CE10320",
        "url": "https://coursesearch04.fcu.edu.tw/CourseOutline.aspx?lang=cht&courseid=1033CE1032011501001"
    },
    {
        "cls_id": "CE10320",
        "url": "https://coursesearch04.fcu.edu.tw/CourseOutline.aspx?lang=cht&courseid=1033CE1032046472001"
    },
    {
        "cls_id": "CE10320",
        "url": "https://coursesearch04.fcu.edu.tw/CourseOutline.aspx?lang=cht&courseid=1033CE1032099861001"
    },
    {
        "cls_id": "CE1032A",
        "url": "https://coursesearch04.fcu.edu.tw/CourseOutline.aspx?lang=cht&courseid=1033CE1032A11501001"
    },
    {
        "cls_id": "CE1032A",
        "url": "https://coursesearch04.fcu.edu.tw/CourseOutline.aspx?lang=cht&courseid=1033CE1032A46472001"
    },
    {
        "cls_id": "CE1032A",
        "url": "https://coursesearch04.fcu.edu.tw/CourseOutline.aspx?lang=cht&courseid=1033CE1032A61530001"
    },
    {
        "cls_id": "CE1032A",
        "url": "https://coursesearch04.fcu.edu.tw/CourseOutline.aspx?lang=cht&courseid=1033CE1032A47090001"
    },
    {
        "cls_id": "CE1032A",
        "url": "https://coursesearch04.fcu.edu.tw/CourseOutline.aspx?lang=cht&courseid=1033CE1032A47580001"
    },
    {
        "cls_id": "CE1032A",
        "url": "https://coursesearch04.fcu.edu.tw/CourseOutline.aspx?lang=cht&courseid=1033CE1032A99861001"
    },
    {
        "cls_id": "CM03310",
        "url": "https://coursesearch04.fcu.edu.tw/CourseOutline.aspx?lang=cht&courseid=1033CM0331026210001"
    },
    {
        "cls_id": "CM03310",
        "url": "https://coursesearch04.fcu.edu.tw/CourseOutline.aspx?lang=cht&courseid=1033CM0331027161001"
    },
    {
        "cls_id": "CM03310",
        "url": "https://coursesearch04.fcu.edu.tw/CourseOutline.aspx?lang=cht&courseid=1033CM0331043130001"
    },
    {
        "cls_id": "CM03310",
        "url": "https://coursesearch04.fcu.edu.tw/CourseOutline.aspx?lang=cht&courseid=1033CM0331006310001"
    },
    {
        "cls_id": "CM03310",
        "url": "https://coursesearch04.fcu.edu.tw/CourseOutline.aspx?lang=cht&courseid=1033CM0331006320001"
    },
    {
        "cls_id": "CM03310",
        "url": "https://coursesearch04.fcu.edu.tw/CourseOutline.aspx?lang=cht&courseid=1033CM0331019002001"
    },
    {
        "cls_id": "CM03310",
        "url": "https://coursesearch04.fcu.edu.tw/CourseOutline.aspx?lang=cht&courseid=1033CM0331041582001"
    },
    {
        "cls_id": "CM03310",
        "url": "https://coursesearch04.fcu.edu.tw/CourseOutline.aspx?lang=cht&courseid=1033CM0331068766001"
    },
    {
        "cls_id": "CM03310",
        "url": "https://coursesearch04.fcu.edu.tw/CourseOutline.aspx?lang=cht&courseid=1033CM0331073451001"
    },
    {
        "cls_id": "CM0331A",
        "url": "https://coursesearch04.fcu.edu.tw/CourseOutline.aspx?lang=cht&courseid=1033CM0331A26210001"
    },
    {
        "cls_id": "CM0331A",
        "url": "https://coursesearch04.fcu.edu.tw/CourseOutline.aspx?lang=cht&courseid=1033CM0331A43130001"
    },
    {
        "cls_id": "CM0331A",
        "url": "https://coursesearch04.fcu.edu.tw/CourseOutline.aspx?lang=cht&courseid=1033CM0331A05370001"
    },
    {
        "cls_id": "CM0331A",
        "url": "https://coursesearch04.fcu.edu.tw/CourseOutline.aspx?lang=cht&courseid=1033CM0331A06170001"
    },
    {
        "cls_id": "CM03320",
        "url": "https://coursesearch04.fcu.edu.tw/CourseOutline.aspx?lang=cht&courseid=1033CM0332012650001"
    },
    {
        "cls_id": "CM03320",
        "url": "https://coursesearch04.fcu.edu.tw/CourseOutline.aspx?lang=cht&courseid=1033CM0332061530001"
    },
    {
        "cls_id": "CM03320",
        "url": "https://coursesearch04.fcu.edu.tw/CourseOutline.aspx?lang=cht&courseid=1033CM0332004851001"
    },
    {
        "cls_id": "CM03320",
        "url": "https://coursesearch04.fcu.edu.tw/CourseOutline.aspx?lang=cht&courseid=1033CM0332005391001"
    },
    {
        "cls_id": "CM03320",
        "url": "https://coursesearch04.fcu.edu.tw/CourseOutline.aspx?lang=cht&courseid=1033CM0332061781001"
    },
    {
        "cls_id": "CM03320",
        "url": "https://coursesearch04.fcu.edu.tw/CourseOutline.aspx?lang=cht&courseid=1033CM0332071786001"
    },
    {
        "cls_id": "CM0332A",
        "url": "https://coursesearch04.fcu.edu.tw/CourseOutline.aspx?lang=cht&courseid=1033CM0332A71786001"
    },
    {
        "cls_id": "CM0332A",
        "url": "https://coursesearch04.fcu.edu.tw/CourseOutline.aspx?lang=cht&courseid=1033CM0332A61530001"
    },
    {
        "cls_id": "CM0332A",
        "url": "https://coursesearch04.fcu.edu.tw/CourseOutline.aspx?lang=cht&courseid=1033CM0332A61781001"
    },
    {
        "cls_id": "CD03310",
        "url": "https://coursesearch04.fcu.edu.tw/CourseOutline.aspx?lang=cht&courseid=1033CD0331027161001"
    },
    {
        "cls_id": "CD03310",
        "url": "https://coursesearch04.fcu.edu.tw/CourseOutline.aspx?lang=cht&courseid=1033CD0331043130001"
    },
    {
        "cls_id": "CD03310",
        "url": "https://coursesearch04.fcu.edu.tw/CourseOutline.aspx?lang=cht&courseid=1033CD0331049732001"
    },
    {
        "cls_id": "CD03310",
        "url": "https://coursesearch04.fcu.edu.tw/CourseOutline.aspx?lang=cht&courseid=1033CD0331012650001"
    },
    {
        "cls_id": "CD03310",
        "url": "https://coursesearch04.fcu.edu.tw/CourseOutline.aspx?lang=cht&courseid=1033CD0331046730001"
    },
    {
        "cls_id": "CD03310",
        "url": "https://coursesearch04.fcu.edu.tw/CourseOutline.aspx?lang=cht&courseid=1033CD0331050091001"
    },
    {
        "cls_id": "CD0331A",
        "url": "https://coursesearch04.fcu.edu.tw/CourseOutline.aspx?lang=cht&courseid=1033CD0331A43130001"
    },
    {
        "cls_id": "CD0331A",
        "url": "https://coursesearch04.fcu.edu.tw/CourseOutline.aspx?lang=cht&courseid=1033CD0331A12905001"
    },
    {
        "cls_id": "CD0331A",
        "url": "https://coursesearch04.fcu.edu.tw/CourseOutline.aspx?lang=cht&courseid=1033CD0331A46730001"
    },
    {
        "cls_id": "CD0331A",
        "url": "https://coursesearch04.fcu.edu.tw/CourseOutline.aspx?lang=cht&courseid=1033CD0331A26210001"
    },
    {
        "cls_id": "CD03320",
        "url": "https://coursesearch04.fcu.edu.tw/CourseOutline.aspx?lang=cht&courseid=1033CD0332049733001"
    },
    {
        "cls_id": "CD03320",
        "url": "https://coursesearch04.fcu.edu.tw/CourseOutline.aspx?lang=cht&courseid=1033CD0332061530001"
    },
    {
        "cls_id": "CD03320",
        "url": "https://coursesearch04.fcu.edu.tw/CourseOutline.aspx?lang=cht&courseid=1033CD0332031123001"
    },
    {
        "cls_id": "CD03320",
        "url": "https://coursesearch04.fcu.edu.tw/CourseOutline.aspx?lang=cht&courseid=1033CD0332043131001"
    },
    {
        "cls_id": "CD03320",
        "url": "https://coursesearch04.fcu.edu.tw/CourseOutline.aspx?lang=cht&courseid=1033CD0332049861001"
    },
    {
        "cls_id": "CD0332A",
        "url": "https://coursesearch04.fcu.edu.tw/CourseOutline.aspx?lang=cht&courseid=1033CD0332A61530001"
    },
    {
        "cls_id": "CD0332A",
        "url": "https://coursesearch04.fcu.edu.tw/CourseOutline.aspx?lang=cht&courseid=1033CD0332A43035001"
    },
    {
        "cls_id": "CD0332A",
        "url": "https://coursesearch04.fcu.edu.tw/CourseOutline.aspx?lang=cht&courseid=1033CD0332A43131001"
    },
    {
        "cls_id": "CD0332A",
        "url": "https://coursesearch04.fcu.edu.tw/CourseOutline.aspx?lang=cht&courseid=1033CD0332A49737001"
    }
]