{
    "d": "[\r\n  {\r\n    \"yearsms\": \"111學年度第1學期\",\r\n    \"yearsms_en\": \"111-1\",\r\n    \"sub_name\": \"智慧機器人概論與實作\",\r\n    \"sub_ename\": \"INTRODUCTION AND IMPLEMENTATION OF INTELLIGENT ROBOTS\",\r\n    \"cls_name\": \"資電學院綜合班\",\r\n    \"cls_ename\": \"College of Information and Electrical Engineering\",\r\n    \"combin_id\": \"CI00101-48899-001\",\r\n    \"mso\": \"選修\",\r\n    \"mso_en\": \"Elective\",\r\n    \"scr_credit\": 3.0,\r\n    \"scr_period\": \"(五)06-08 科航801 蔡明翰,林佩君,林維崙\",\r\n    \"scr_period_eng\": \"(Fri)06-08  Ming-Han Tsai,Pei-Chun Lin,Wei-Lun Lin\",\r\n    \"language\": \"中文\",\r\n    \"lang_ename\": \"Chinese\",\r\n    \"sub_id3\": \"IEE3011\",\r\n    \"scr_periodonly\": \"(五)06-08\",\r\n    \"scr_periodonly_eng\": \"(Fri)06-08\",\r\n    \"scr_room\": \"科航801\",\r\n    \"scr_room_eng\": \" \",\r\n    \"scr_teacher\": \"蔡明翰,林佩君,林維崙\",\r\n    \"scr_teacher_eng\": \"Ming-Han Tsai,Pei-Chun Lin,Wei-Lun Lin\",\r\n    \"soft_mark\": \"N\",\r\n    \"emp_ename\": \"Pei-Chun Lin                                                \"\r\n  }\r\n]"
}